psychopy_neuroplaypro_neurolab/__init__.py
psychopy_neuroplaypro_neurolab/neuroplay.py
psychopy_neuroplaypro_neurolab/neuroplay_record/__init__.py
psychopy_neuroplaypro_neurolab/neuroplay_record/classic/neuroplay_record.png
psychopy_neuroplaypro_neurolab/neuroplay_record/classic/neuroplay_record@2x.png
psychopy_neuroplaypro_neurolab/neuroplay_record/dark/neuroplay_record.png
psychopy_neuroplaypro_neurolab/neuroplay_record/dark/neuroplay_record@2x.png
psychopy_neuroplaypro_neurolab/neuroplay_record/light/neuroplay_record.png
psychopy_neuroplaypro_neurolab/neuroplay_record/light/neuroplay_record@2x.png
psychopy_neuroplaypro_neurolab-0.1.2.dist-info/licenses/LICENSE
psychopy_neuroplaypro_neurolab-0.1.2.dist-info/METADATA
psychopy_neuroplaypro_neurolab-0.1.2.dist-info/WHEEL
psychopy_neuroplaypro_neurolab-0.1.2.dist-info/entry_points.txt
psychopy_neuroplaypro_neurolab-0.1.2.dist-info/top_level.txt
psychopy_neuroplaypro_neurolab-0.1.2.dist-info/RECORD
