Metadata-Version: 2.4
Name: psychopy-neuroplaypro-neurolab
Version: 0.1.2
Summary: PsychoPy plugin to support NeuroPlayPro EEG triggers.
Author-email: Enicast <enicaster@gmail.com>
Requires-Python: >=3.8
License-File: LICENSE
Requires-Dist: websocket-client
Dynamic: license-file
